da/__init__.py
da/p7core_2025_12_10/FindNative.py
da/p7core_2025_12_10/__init__.py
da/p7core_2025_12_10/archives.py
da/p7core_2025_12_10/blackbox.py
da/p7core_2025_12_10/exceptions.py
da/p7core_2025_12_10/license.py
da/p7core_2025_12_10/loggers.py
da/p7core_2025_12_10/options.py
da/p7core_2025_12_10/parameters.py
da/p7core_2025_12_10/result.py
da/p7core_2025_12_10/safe_pickle.py
da/p7core_2025_12_10/shared.py
da/p7core_2025_12_10/six.py
da/p7core_2025_12_10/status.py
da/p7core_2025_12_10/watchers.py
da/p7core_2025_12_10/batch/__init__.py
da/p7core_2025_12_10/batch/batch_manager.py
da/p7core_2025_12_10/batch/command.py
da/p7core_2025_12_10/batch/utils.py
da/p7core_2025_12_10/bin/linux-x64/libgeneric_tools-2025.12.10-linux-x64-gcc53-s.so
da/p7core_2025_12_10/bin/linux-x64/libgtmodel-2025.12.10-linux-x64-gcc53-s.so
da/p7core_2025_12_10/examples/__init__.py
da/p7core_2025_12_10/examples/example_joint_usage.py
da/p7core_2025_12_10/examples/gtapprox/EvaluateGTModel.java
da/p7core_2025_12_10/examples/gtapprox/__init__.py
da/p7core_2025_12_10/examples/gtapprox/example_adaptive_doe.py
da/p7core_2025_12_10/examples/gtapprox/example_additive_gp.py
da/p7core_2025_12_10/examples/gtapprox/example_axis_rotations.py
da/p7core_2025_12_10/examples/gtapprox/example_export_to_c.py
da/p7core_2025_12_10/examples/gtapprox/example_get_validity_domain.py
da/p7core_2025_12_10/examples/gtapprox/example_gtapprox.py
da/p7core_2025_12_10/examples/gtapprox/example_gtmodel.c
da/p7core_2025_12_10/examples/gtapprox/example_internal_validation.py
da/p7core_2025_12_10/examples/gtapprox/example_memory_control.py
da/p7core_2025_12_10/examples/gtapprox/example_moa_basic.py
da/p7core_2025_12_10/examples/gtapprox/example_moa_discontinuous_func.py
da/p7core_2025_12_10/examples/gtapprox/example_output_variances.py
da/p7core_2025_12_10/examples/gtapprox/example_shap.ipynb
da/p7core_2025_12_10/examples/gtapprox/example_smart_selection.py
psevencore-2025.12.10.dist-info/licenses/LICENSE
psevencore-2025.12.10.dist-info/METADATA
psevencore-2025.12.10.dist-info/WHEEL
psevencore-2025.12.10.dist-info/top_level.txt
psevencore-2025.12.10.dist-info/RECORD
