Metadata-Version: 2.4
Name: psevencore
Version: 2025.12.10
Summary: pSeven Core is an integrated toolkit for design space exploration, optimization, and predictive modeling.
Author-email: pSeven SAS <info@pseven.io>
Maintainer-email: pSeven SAS <info@pseven.io>
License: # End-User License Agreement
Project-URL: Homepage, https://www.pseven.io/product/pseven-core/
Project-URL: Documentation, https://www.pseven.io/product/pseven-core/manual/
Project-URL: Changelog, https://www.pseven.io/product/pseven-core/manual/latest/support/changelog.html
Project-URL: Support, https://www.pseven.io/support.html
Keywords: adaptive design,adaptive doe,approximation,approximation model,approximation modeling,approximator,box-behnken,correlation analysis,design exploration,design of experiments,design optimization,design space,difference approximation,dimension reduction,doe,engineering,engineering optimization,feature importance,feature scoring,feature selection,fmi,fmu,fractional factorial,gaussian processes,gradient optimization,kendall,latin hypercube sampling,low discrepancy sequence,mixed integer,mix
Classifier: Development Status :: 5 - Production/Stable
Classifier: Intended Audience :: Developers
Classifier: Intended Audience :: Manufacturing
Classifier: Intended Audience :: Science/Research
Classifier: License :: Other/Proprietary License
Classifier: Operating System :: Microsoft :: Windows
Classifier: Operating System :: POSIX
Classifier: Operating System :: POSIX :: Linux
Classifier: Operating System :: Unix
Classifier: Programming Language :: C
Classifier: Programming Language :: Java
Classifier: Programming Language :: Python
Classifier: Programming Language :: Python :: 2.7
Classifier: Programming Language :: Python :: 3
Classifier: Topic :: Software Development :: Libraries
Classifier: Topic :: Software Development :: Libraries :: Java Libraries
Classifier: Topic :: Scientific/Engineering
Classifier: Topic :: Scientific/Engineering :: Artificial Intelligence
Classifier: Topic :: Scientific/Engineering :: Information Analysis
Classifier: Topic :: Scientific/Engineering :: Mathematics
Classifier: Operating System :: POSIX :: Linux
Classifier: Operating System :: Unix
Requires-Python: !=3.0.*,!=3.1.*,!=3.2.*,!=3.3.*,!=3.4.*,!=3.5.*,>=2.7
License-File: LICENSE
Requires-Dist: numpy<2,>=1.16; python_version ~= "2.7"
Requires-Dist: numpy>=1.16; python_version >= "3.6"
Dynamic: license-file
